lib/__init__.py
lib/logging.py
lib/notarius.py
lib/utils.py
notarius-0.2.2.data/scripts/notarius
notarius-0.2.2.dist-info/LICENSE
notarius-0.2.2.dist-info/METADATA
notarius-0.2.2.dist-info/WHEEL
notarius-0.2.2.dist-info/top_level.txt
notarius-0.2.2.dist-info/RECORD
