Metadata-Version: 2.1
Name: notarius
Version: 0.2.2
Summary: Tool to notarize a macOS dmg
Home-page: https://github.com/Devolutions/notarius
Author: Jean-Francois Theroux
Author-email: jftheroux@devolutions.net
License: MIT
Keywords: apple,macos,dmg,notarize
Platform: any
Classifier: Programming Language :: Python :: 3
Classifier: License :: OSI Approved :: MIT License
Classifier: Operating System :: OS Independent
Requires-Dist: requests
